snippet/__init__.py
snippet/snippet.py
snippet/.snippet/__init__.py
snippet/.snippet/snippet_profile.py
snippet/.snippet/codecs/add.py
snippet/.snippet/codecs/addslashes.py
snippet/.snippet/codecs/b64.py
snippet/.snippet/codecs/capfirst.py
snippet/.snippet/codecs/center.py
snippet/.snippet/codecs/date.py
snippet/.snippet/codecs/dquote.py
snippet/.snippet/codecs/first.py
snippet/.snippet/codecs/join.py
snippet/.snippet/codecs/last.py
snippet/.snippet/codecs/length.py
snippet/.snippet/codecs/ljust.py
snippet/.snippet/codecs/lower.py
snippet/.snippet/codecs/md5.py
snippet/.snippet/codecs/rjust.py
snippet/.snippet/codecs/safename.py
snippet/.snippet/codecs/sha1.py
snippet/.snippet/codecs/sha256.py
snippet/.snippet/codecs/sha512.py
snippet/.snippet/codecs/squote.py
snippet/.snippet/codecs/title.py
snippet/.snippet/codecs/truncatechars.py
snippet/.snippet/codecs/truncatewords.py
snippet/.snippet/codecs/upper.py
snippet/.snippet/codecs/url.py
snippet/.snippet/codecs/urlplus.py
snippet/.snippet/codecs/wordcount.py
tests/__init__.py
tests/main.py
snippet_cli-2.1.0.dist-info/LICENSE
snippet_cli-2.1.0.dist-info/METADATA
snippet_cli-2.1.0.dist-info/WHEEL
snippet_cli-2.1.0.dist-info/entry_points.txt
snippet_cli-2.1.0.dist-info/top_level.txt
snippet_cli-2.1.0.dist-info/RECORD
