Metadata-Version: 2.1
Name: snippet-cli
Version: 2.1.0
Summary: An advanced snippet manager for the command-line.
Home-page: https://github.com/bytebutcher/snippet
Author: bytebutcher
Author-email: thomas.engel.web@gmail.com
License: GPL-3.0
Classifier: Programming Language :: Python :: 3
Classifier: Operating System :: OS Independent
License-File: LICENSE
Requires-Dist: pyparsing ==3.1.1
Requires-Dist: argcomplete ==3.1.6
Requires-Dist: iterfzf ==1.1.0.44.0
Requires-Dist: colorama ==0.4.6
